damuta/__init__.py
damuta/base.py
damuta/callbacks.py
damuta/constants.py
damuta/models.py
damuta/plotting.py
damuta/sim.py
damuta/utils.py
tests/__init__.py
tests/conftest.py
tests/test_base.py
tests/test_model_init.py
tests/test_model_methods.py
tests/test_model_opt_method.py
tests/test_model_signature_extraction.py
tests/test_utils.py
damuta-1.0.7.dist-info/LICENSE
damuta-1.0.7.dist-info/METADATA
damuta-1.0.7.dist-info/WHEEL
damuta-1.0.7.dist-info/top_level.txt
damuta-1.0.7.dist-info/RECORD
