Metadata-Version: 2.1
Name: damuta
Version: 1.0.7
Summary: Dirichlet allocation of mutations in cancer genomes
Home-page: https://github.com/morrislab/damuta
Author: Cait Harrigan
Author-email: charrigan@cs.toronto.edu
Project-URL: Bug Tracker, https://github.com/morrislab/damuta/issues
Classifier: Programming Language :: Python :: 3
Classifier: Development Status :: 1 - Planning
Classifier: License :: OSI Approved :: MIT License
Classifier: Operating System :: Unix
Requires-Python: >=3.8
License-File: LICENSE
Provides-Extra: dev
Requires-Dist: pytest; extra == "dev"
Requires-Dist: pytest-cov; extra == "dev"
Requires-Dist: sphinx>=1.4; extra == "dev"
Requires-Dist: nbsphinx; extra == "dev"
Requires-Dist: sphinx-gallery; extra == "dev"
Requires-Dist: nbsphinx-link; extra == "dev"
Requires-Dist: ipykernel; extra == "dev"
Requires-Dist: sphinx-rtd-theme; extra == "dev"
